germansentiment/__init__.py
germansentiment/sentimentmodel.py
germansentiment/sentimentmodel_test.py
germansentiment-1.1.0.dist-info/LICENSE
germansentiment-1.1.0.dist-info/METADATA
germansentiment-1.1.0.dist-info/WHEEL
germansentiment-1.1.0.dist-info/top_level.txt
germansentiment-1.1.0.dist-info/RECORD
