Metadata-Version: 2.1
Name: germansentiment
Version: 1.1.0
Summary: A python package for german language sentiment classification.
Home-page: https://github.com/oliverguhr/german-sentiment-lib
Author: Oliver Guhr
Author-email: oliver.guhr@htw-dresden.de
License: UNKNOWN
Platform: UNKNOWN
Classifier: Programming Language :: Python :: 3
Classifier: License :: OSI Approved :: MIT License
Classifier: Operating System :: OS Independent
Requires-Python: >=3.6
License-File: LICENSE
Requires-Dist: torch (>=1.8.1)
Requires-Dist: transformers
